llama_index/tools/weather/__init__.py
llama_index/tools/weather/base.py
llama_index_tools_weather-0.4.1.dist-info/METADATA
llama_index_tools_weather-0.4.1.dist-info/WHEEL
llama_index_tools_weather-0.4.1.dist-info/licenses/LICENSE
llama_index_tools_weather-0.4.1.dist-info/RECORD
