Metadata-Version: 2.4
Name: llama-index-tools-weather
Version: 0.4.1
Summary: llama-index tools weather integration
Author-email: Your Name <you@example.com>
Maintainer: logan-markewich
License-Expression: MIT
License-File: LICENSE
Requires-Python: <4.0,>=3.9
Requires-Dist: llama-index-core<0.15,>=0.13.0
